spire/__init__.py
spire/xls/AddInFunctionsCollection.py
spire/xls/AddtionalFormatWrapper.py
spire/xls/AlertStyleType.py
spire/xls/ArcShapeCollection.py
spire/xls/AutoFiltersCollection.py
spire/xls/AutoFitterOptions.py
spire/xls/AutoFormatOptions.py
spire/xls/AutoFormatType.py
spire/xls/AutoSortScope.py
spire/xls/Average.py
spire/xls/AverageType.py
spire/xls/AxisLineIdentifierType.py
spire/xls/AxisTextDirectionType.py
spire/xls/AxisType.py
spire/xls/AxisTypes.py
spire/xls/BaseFormatType.py
spire/xls/BordersCollection.py
spire/xls/BordersCollectionArrayWrapper.py
spire/xls/BordersLineType.py
spire/xls/BubbleSizeType.py
spire/xls/BuiltInDocumentProperties.py
spire/xls/BuiltInPropertyType.py
spire/xls/BuiltInStyles.py
spire/xls/ButtonShapeCollection.py
spire/xls/CategoryType.py
spire/xls/CellBaseStyle.py
spire/xls/CellBorder.py
spire/xls/CellDataType.py
spire/xls/CellFormatType.py
spire/xls/CellRange.py
spire/xls/CellStyle.py
spire/xls/CellStyleFlag.py
spire/xls/CellStyleObject.py
spire/xls/CellValueChangedEventArgs.py
spire/xls/CellValueChangedEventHandler.py
spire/xls/Chart.py
spire/xls/ChartArea.py
spire/xls/ChartBackgroundMode.py
spire/xls/ChartBaseUnitType.py
spire/xls/ChartBorder.py
spire/xls/ChartCategoryAxis.py
spire/xls/ChartDataLabels.py
spire/xls/ChartDataPoint.py
spire/xls/ChartDataPointsCollection.py
spire/xls/ChartDataTable.py
spire/xls/ChartDisplayUnitType.py
spire/xls/ChartDropBar.py
spire/xls/ChartFormat.py
spire/xls/ChartFormatCollection.py
spire/xls/ChartGridLine.py
spire/xls/ChartInterior.py
spire/xls/ChartLegend.py
spire/xls/ChartLegendEntriesColl.py
spire/xls/ChartLegendEntry.py
spire/xls/ChartLinePatternType.py
spire/xls/ChartLineWeightType.py
spire/xls/ChartMarkerType.py
spire/xls/ChartPageSetup.py
spire/xls/ChartParagraphType.py
spire/xls/ChartPieType.py
spire/xls/ChartPlotArea.py
spire/xls/ChartPlotEmptyType.py
spire/xls/ChartSerie.py
spire/xls/ChartSerieDataFormat.py
spire/xls/ChartSeries.py
spire/xls/ChartSeriesAxis.py
Spire.Xls.Free-14.12.4.dist-info/METADATA
Spire.Xls.Free-14.12.4.dist-info/WHEEL
Spire.Xls.Free-14.12.4.dist-info/top_level.txt
Spire.Xls.Free-14.12.4.dist-info/RECORD
